{
	"animations": [
		{
			"loop": false,
			"offsets": [
				-5,
				0
			],
			"anim": "idle",
			"fps": 24,
			"name": "BF idle dance",
			"indices": []
		},
		{
			"loop": false,
			"offsets": [
				5,
				-6
			],
			"anim": "singLEFT",
			"fps": 24,
			"name": "BF NOTE LEFT0",
			"indices": []
		},
		{
			"loop": false,
			"offsets": [
				-20,
				-51
			],
			"anim": "singDOWN",
			"fps": 24,
			"name": "BF NOTE DOWN0",
			"indices": []
		},
		{
			"loop": false,
			"offsets": [
				-46,
				27
			],
			"anim": "singUP",
			"fps": 24,
			"name": "BF NOTE UP0",
			"indices": []
		},
		{
			"loop": false,
			"offsets": [
				-48,
				-7
			],
			"anim": "singRIGHT",
			"fps": 24,
			"name": "BF NOTE RIGHT0",
			"indices": []
		},
		{
			"loop": false,
			"offsets": [
				7,
				3
			],
			"anim": "singLEFTmiss",
			"fps": 24,
			"name": "BF NOTE LEFT MISS",
			"indices": []
		},
		{
			"loop": false,
			"offsets": [
				-21,
				-21
			],
			"anim": "singDOWNmiss",
			"fps": 24,
			"name": "BF NOTE DOWN MISS",
			"indices": []
		},
		{
			"loop": false,
			"offsets": [
				-44,
				27
			],
			"anim": "singUPmiss",
			"fps": 24,
			"name": "BF NOTE UP MISS",
			"indices": []
		},
		{
			"loop": false,
			"offsets": [
				-45,
				-9
			],
			"anim": "singRIGHTmiss",
			"fps": 24,
			"name": "BF NOTE RIGHT MISS",
			"indices": []
		},
		{
			"offsets": [
				19,
				157
			],
			"loop": true,
			"fps": 24,
			"anim": "hey",
			"indices": [],
			"name": "bf-omnimanButt0"
		},
		{
			"offsets": [
				120,
				19
			],
			"loop": true,
			"fps": 24,
			"anim": "oh shit",
			"indices": [],
			"name": "bf-ouShit0"
		}
	],
	"no_antialiasing": false,
	"image": "characters/bf-pom-fum",
	"position": [
		370,
		340
	],
	"healthicon": "bf",
	"flip_x": true,
	"healthbar_colors": [
		49,
		176,
		209
	],
	"camera_position": [
		100,
		20
	],
	"sing_duration": 4,
	"scale": 1
}