<?xml version="1.0" encoding="utf-8"?>
<TextureAtlas imagePath="CoCaine.png">
	<!-- Created with Adobe Animate version 22.0.2.168 -->
	<!-- http://www.adobe.com/products/animate.html -->
	<SubTexture name="CoCaine-down0000" x="0" y="0" width="536" height="574" frameX="0" frameY="-114" frameWidth="536" frameHeight="688"/>
	<SubTexture name="CoCaine-down0001" x="536" y="0" width="519" height="585" frameX="-7" frameY="-71" frameWidth="536" frameHeight="688"/>
	<SubTexture name="CoCaine-down0002" x="1055" y="0" width="519" height="573" frameX="-7" frameY="-14" frameWidth="536" frameHeight="688"/>
	<SubTexture name="CoCaine-down0003" x="1574" y="0" width="519" height="573" frameX="-7" frameY="-14" frameWidth="536" frameHeight="688"/>
	<SubTexture name="CoCaine-down0004" x="2093" y="0" width="519" height="572" frameX="-7" frameY="-8" frameWidth="536" frameHeight="688"/>
	<SubTexture name="CoCaine-down0005" x="2612" y="0" width="519" height="572" frameX="-7" frameY="-8" frameWidth="536" frameHeight="688"/>
	<SubTexture name="CoCaine-down0006" x="3131" y="0" width="519" height="571" frameX="-7" frameY="-4" frameWidth="536" frameHeight="688"/>
	<SubTexture name="CoCaine-down0007" x="3650" y="0" width="519" height="571" frameX="-7" frameY="-4" frameWidth="536" frameHeight="688"/>
	<SubTexture name="CoCaine-down0008" x="4169" y="0" width="519" height="572" frameX="-7" frameY="0" frameWidth="536" frameHeight="688"/>
	<SubTexture name="CoCaine-down0009" x="4688" y="0" width="519" height="572" frameX="-7" frameY="0" frameWidth="536" frameHeight="688"/>
	<SubTexture name="CoCaine-idle0000" x="5207" y="0" width="475" height="738" frameX="-8" frameY="-7" frameWidth="483" frameHeight="749"/>
	<SubTexture name="CoCaine-idle0001" x="5682" y="0" width="462" height="742" frameX="-14" frameY="-3" frameWidth="483" frameHeight="749"/>
	<SubTexture name="CoCaine-idle0002" x="6144" y="0" width="472" height="749" frameX="-7" frameY="0" frameWidth="483" frameHeight="749"/>
	<SubTexture name="CoCaine-idle0003" x="6616" y="0" width="483" height="746" frameX="0" frameY="-3" frameWidth="483" frameHeight="749"/>
	<SubTexture name="CoCaine-idle0004" x="7099" y="0" width="459" height="743" frameX="-18" frameY="-5" frameWidth="483" frameHeight="749"/>
	<SubTexture name="CoCaine-idle0005" x="7558" y="0" width="447" height="739" frameX="-21" frameY="-9" frameWidth="483" frameHeight="749"/>
	<SubTexture name="CoCaine-idle0006" x="0" y="749" width="450" height="741" frameX="-22" frameY="-5" frameWidth="483" frameHeight="749"/>
	<SubTexture name="CoCaine-idle0007" x="450" y="749" width="465" height="745" frameX="-15" frameY="-1" frameWidth="483" frameHeight="749"/>
	<SubTexture name="CoCaine-left0000" x="915" y="749" width="864" height="542" frameX="0" frameY="-22" frameWidth="877" frameHeight="586"/>
	<SubTexture name="CoCaine-left0001" x="1779" y="749" width="751" height="548" frameX="-124" frameY="-22" frameWidth="877" frameHeight="586"/>
	<SubTexture name="CoCaine-left0002" x="2530" y="749" width="682" height="576" frameX="-195" frameY="-5" frameWidth="877" frameHeight="586"/>
	<SubTexture name="CoCaine-left0003" x="3212" y="749" width="682" height="576" frameX="-195" frameY="-5" frameWidth="877" frameHeight="586"/>
	<SubTexture name="CoCaine-left0004" x="3894" y="749" width="670" height="578" frameX="-207" frameY="-5" frameWidth="877" frameHeight="586"/>
	<SubTexture name="CoCaine-left0005" x="4564" y="749" width="670" height="578" frameX="-207" frameY="-5" frameWidth="877" frameHeight="586"/>
	<SubTexture name="CoCaine-left0006" x="5234" y="749" width="663" height="579" frameX="-213" frameY="-5" frameWidth="877" frameHeight="586"/>
	<SubTexture name="CoCaine-left0007" x="5897" y="749" width="663" height="579" frameX="-213" frameY="-5" frameWidth="877" frameHeight="586"/>
	<SubTexture name="CoCaine-left0008" x="6560" y="749" width="650" height="586" frameX="-226" frameY="0" frameWidth="877" frameHeight="586"/>
	<SubTexture name="CoCaine-left0009" x="7210" y="749" width="650" height="586" frameX="-226" frameY="0" frameWidth="877" frameHeight="586"/>
	<SubTexture name="CoCaine-right0000" x="0" y="1494" width="613" height="679" frameX="-54" frameY="-16" frameWidth="667" frameHeight="699"/>
	<SubTexture name="CoCaine-right0001" x="613" y="1494" width="530" height="695" frameX="-47" frameY="0" frameWidth="667" frameHeight="699"/>
	<SubTexture name="CoCaine-right0002" x="1143" y="1494" width="478" height="676" frameX="-33" frameY="-19" frameWidth="667" frameHeight="699"/>
	<SubTexture name="CoCaine-right0003" x="1621" y="1494" width="484" height="679" frameX="-27" frameY="-19" frameWidth="667" frameHeight="699"/>
	<SubTexture name="CoCaine-right0004" x="2105" y="1494" width="495" height="667" frameX="-9" frameY="-29" frameWidth="667" frameHeight="699"/>
	<SubTexture name="CoCaine-right0005" x="2600" y="1494" width="492" height="667" frameX="-12" frameY="-29" frameWidth="667" frameHeight="699"/>
	<SubTexture name="CoCaine-right0006" x="3092" y="1494" width="496" height="668" frameX="-3" frameY="-31" frameWidth="667" frameHeight="699"/>
	<SubTexture name="CoCaine-right0007" x="3588" y="1494" width="496" height="668" frameX="-3" frameY="-31" frameWidth="667" frameHeight="699"/>
	<SubTexture name="CoCaine-right0008" x="4084" y="1494" width="494" height="667" frameX="-4" frameY="-32" frameWidth="667" frameHeight="699"/>
	<SubTexture name="CoCaine-right0009" x="4578" y="1494" width="497" height="667" frameX="0" frameY="-32" frameWidth="667" frameHeight="699"/>
	<SubTexture name="CoCaine-right0010" x="5075" y="1494" width="495" height="667" frameX="-3" frameY="-32" frameWidth="667" frameHeight="699"/>
	<SubTexture name="CoCaine-right0011" x="4578" y="1494" width="497" height="667" frameX="0" frameY="-32" frameWidth="667" frameHeight="699"/>
	<SubTexture name="CoCaine-right0012" x="5075" y="1494" width="495" height="667" frameX="-3" frameY="-32" frameWidth="667" frameHeight="699"/>
	<SubTexture name="CoCaine-right0013" x="4578" y="1494" width="497" height="667" frameX="0" frameY="-32" frameWidth="667" frameHeight="699"/>
	<SubTexture name="CoCaine-right0014" x="5075" y="1494" width="495" height="667" frameX="-3" frameY="-32" frameWidth="667" frameHeight="699"/>
	<SubTexture name="CoCaine-right0015" x="4578" y="1494" width="497" height="667" frameX="0" frameY="-32" frameWidth="667" frameHeight="699"/>
	<SubTexture name="CoCaine-right0016" x="5075" y="1494" width="495" height="667" frameX="-3" frameY="-32" frameWidth="667" frameHeight="699"/>
	<SubTexture name="CoCaine-right0017" x="4578" y="1494" width="497" height="667" frameX="0" frameY="-32" frameWidth="667" frameHeight="699"/>
	<SubTexture name="CoCaine-right0018" x="5075" y="1494" width="495" height="667" frameX="-3" frameY="-32" frameWidth="667" frameHeight="699"/>
	<SubTexture name="CoCaine-right0019" x="4578" y="1494" width="497" height="667" frameX="0" frameY="-32" frameWidth="667" frameHeight="699"/>
	<SubTexture name="CoCaine-up0000" x="5570" y="1494" width="816" height="1002" frameX="0" frameY="0" frameWidth="816" frameHeight="1021"/>
	<SubTexture name="CoCaine-up0001" x="6386" y="1494" width="798" height="947" frameX="-7" frameY="-44" frameWidth="816" frameHeight="1021"/>
	<SubTexture name="CoCaine-up0002" x="7184" y="1494" width="802" height="877" frameX="-5" frameY="-129" frameWidth="816" frameHeight="1021"/>
	<SubTexture name="CoCaine-up0003" x="0" y="2496" width="793" height="877" frameX="-11" frameY="-129" frameWidth="816" frameHeight="1021"/>
	<SubTexture name="CoCaine-up0004" x="793" y="2496" width="802" height="855" frameX="-5" frameY="-162" frameWidth="816" frameHeight="1021"/>
	<SubTexture name="CoCaine-up0005" x="1595" y="2496" width="796" height="855" frameX="-7" frameY="-162" frameWidth="816" frameHeight="1021"/>
	<SubTexture name="CoCaine-up0006" x="2391" y="2496" width="802" height="842" frameX="-5" frameY="-178" frameWidth="816" frameHeight="1021"/>
	<SubTexture name="CoCaine-up0007" x="3193" y="2496" width="795" height="842" frameX="-8" frameY="-178" frameWidth="816" frameHeight="1021"/>
	<SubTexture name="CoCaine-up0008" x="3988" y="2496" width="802" height="836" frameX="-5" frameY="-185" frameWidth="816" frameHeight="1021"/>
	<SubTexture name="CoCaine-up0009" x="4790" y="2496" width="796" height="836" frameX="-8" frameY="-185" frameWidth="816" frameHeight="1021"/>
</TextureAtlas>
